{"id":16348,"name":"Dog rescue plan (China)","desc":"0J7Qv9C40YHQsNC90LjRjyDQvdC10YIu","add":"9 Апр 2012 15:43","dwn":940,"upl":"wakko","cat":"Аркады","cmm":2,"s3D":false,"bt":false,"rating":{"rtg":"0/1","ups":0,"dws":1,"scr":-1},"files":[{"text":"128x128 : SE K,J,Z300 Chn  \r\n","links":[{"url":"http://rugame.mobi/china/16369/n7260.jar","file":"n7260.5.jar","type":"JAR"},{"url":"http://rugame.mobi/china/16369/1/n7260.jad","file":"n7260.5.jad","type":"JAD"}],"size":77},{"text":"128x160 : S40 2ed Chn  \r\n","links":[{"url":"http://rugame.mobi/china/16377/n6101.jar","file":"n6101.16.jar","type":"JAR"},{"url":"http://rugame.mobi/china/16377/1/n6101.jad","file":"n6101.16.jad","type":"JAD"}],"size":114},{"text":"128x160 : SE K310,K500,K510, W200,Z530 Chn  \r\n","links":[{"url":"http://rugame.mobi/china/16367/k506.jar","file":"k506.4.jar","type":"JAR"},{"url":"http://rugame.mobi/china/16367/1/k506.jad","file":"k506.4.jad","type":"JAD"}],"size":114},{"text":"128x160 : MOT L2,L6,C261 Chn  \r\n","links":[{"url":"http://rugame.mobi/china/16375/l6.jar","file":"l6.jar","type":"JAR"},{"url":"http://rugame.mobi/china/16375/1/l6.jad","file":"l6.jad","type":"JAD"}],"size":99},{"text":"176x208 : S60 2ed Chn  \r\n","links":[{"url":"http://rugame.mobi/china/16364/n7610.jar","file":"n7610.44.jar","type":"JAR"},{"url":"http://rugame.mobi/china/16364/1/n7610.jad","file":"n7610.44.jad","type":"JAD"}],"size":250},{"text":"176x220 : SE K700,K750,K550, K610,W350,W810,Z710 Chn  \r\n","links":[{"url":"http://rugame.mobi/china/16366/k700.jar","file":"k700.21.jar","type":"JAR"},{"url":"http://rugame.mobi/china/16366/1/k700.jad","file":"k700.21.jad","type":"JAD"}],"size":251},{"text":"176x220 : MOT E398,E770,L7,E1 Chn  \r\n","links":[{"url":"http://rugame.mobi/china/16380/e398.jar","file":"e398.5.jar","type":"JAR"},{"url":"http://rugame.mobi/china/16380/1/e398.jad","file":"e398.5.jad","type":"JAD"}],"size":192},{"text":"240x320 : S40 3ed Chn  \r\n","links":[{"url":"http://rugame.mobi/china/16373/n7370.jar","file":"n7370.25.jar","type":"JAR"},{"url":"http://rugame.mobi/china/16373/1/n7370.jad","file":"n7370.25.jad","type":"JAD"}],"size":324},{"text":"240x320 : S60 3ed Chn  \r\n","links":[{"url":"http://rugame.mobi/china/16371/n73.jar","file":"n73.71.jar","type":"JAR"},{"url":"http://rugame.mobi/china/16371/1/n73.jad","file":"n73.71.jad","type":"JAD"}],"size":332},{"text":"240x320 : SE K770,K800,S500 ,T650,W850 Chn  \r\n","links":[{"url":"http://rugame.mobi/china/16378/k790.jar","file":"k790.14.jar","type":"JAR"},{"url":"http://rugame.mobi/china/16378/1/k790.jad","file":"k790.14.jad","type":"JAD"}],"size":332},{"text":"240х320 : SE (UIQ3) M600,P1, W950,W960 Chn  \r\n","links":[{"url":"http://rugame.mobi/china/16376/s700.jar","file":"s700.1.jar","type":"JAR"},{"url":"http://rugame.mobi/china/16376/1/s700.jad","file":"s700.1.jad","type":"JAD"}],"size":312},{"text":"240х320 : SE (UIQ3) M600,P1, W950,W960 Chn  \r\n","links":[{"url":"http://rugame.mobi/china/16379/w958.jar","file":"w958.1.jar","type":"JAR"},{"url":"http://rugame.mobi/china/16379/1/w958.jad","file":"w958.1.jad","type":"JAD"}],"size":332},{"text":"240x320 : MOT E2,Z6,V8,U9,ZN5 Chn  \r\n","links":[{"url":"http://rugame.mobi/china/16372/e2.jar","file":"e2.12.jar","type":"JAR"},{"url":"http://rugame.mobi/china/16372/1/e2.jad","file":"e2.12.jad","type":"JAD"}],"size":323},{"text":"240x320 : MOT v8 Chn  \r\n","links":[{"url":"http://rugame.mobi/china/16374/v8.jar","file":"v8.1.jar","type":"JAR"},{"url":"http://rugame.mobi/china/16374/1/v8.jad","file":"v8.1.jad","type":"JAD"}],"size":311},{"text":"240x320 : MOT Touch Chn  \r\n","links":[{"url":"http://rugame.mobi/china/16368/e6.jar","file":"e6.15.jar","type":"JAR"},{"url":"http://rugame.mobi/china/16368/1/e6.jad","file":"e6.15.jad","type":"JAD"}],"size":312},{"text":"320x240 : S60 3ed Chn  \r\n","links":[{"url":"http://rugame.mobi/china/16365/e62.jar","file":"e62.45.jar","type":"JAR"},{"url":"http://rugame.mobi/china/16365/1/e62.jad","file":"e62.45.jad","type":"JAD"}],"size":320},{"text":"360x640 : S60 5ed Chn<br/>360x640 : SE U1i(Satio), U5I(VIVAZ),U8i Chn<br/>360x640 : SAM i8910, i8910U,M8000 Chn  \r\n<br>","links":[{"url":"http://rugame.mobi/china/16370/n97.jar","file":"n97.43.jar","type":"JAR"},{"url":"http://rugame.mobi/china/16370/1/n97.jad","file":"n97.43.jad","type":"JAD"}],"size":269}]}