{"name":"The dawn of the dark edge of the three legendary assassins 3 (China)","desc":"0J7Qv9C40YHQsNC90LjRjyDQvdC10YIu","add":"20 Сен 2010 21:52","dwn":2228,"vnd":"Yintelaisi ","upl":"STOCKER","cat":"Action","cmm":0,"rating":{"rtg":"0/0"},"files":[{"text":"128x160 : S40 2ed Chn<br/>128x160 : SE K310,K500,K510,W200,Z530 Chn  \r\n","links":[{"file":"sek506.jar"},{"file":"sek506.jad"}],"size":229},{"text":"176x208 : S60 2ed Chn  \r\n","links":[{"file":"n7610.355.jar"},{"file":"n7610.355.jad"}],"size":238},{"text":"176x220 : SE K700,K750 Chn<br/>176x220 : SE K550,K610,W350,W810,Z710 Chn  \r\n","links":[{"file":"sek700.jar"},{"file":"sek700.jad"}],"size":232},{"text":"240x320 : S40 3ed Chn  \r\n","links":[{"file":"n7370.265.jar"},{"file":"n7370.265.jad"}],"size":234},{"text":"240x320 : S60 3ed Chn  \r\n","links":[{"file":"n73.563.jar"},{"file":"n73.563.jad"}],"size":240},{"text":"240x320 : SE K770,K800,S500,T650,W850 Chn  \r\n","links":[{"file":"sek790.jar"},{"file":"sek790.jad"}],"size":234}]}