{"id":6558,"name":"Recorded in the early Tang Fengyun (China)","desc":"0J7Qv9C40YHQsNC90LjRjyDQvdC10YIu","add":"25 Окт 2010 17:42","dwn":1357,"vnd":"JAR","upl":"STOCKER","cat":"Rpg","cmm":6,"s3D":false,"bt":false,"rating":{"rtg":"0/1","ups":0,"dws":1,"scr":-1},"files":[{"text":"176x208 : S60 2ed Chn  \r\n","links":[{"url":"http://rugame.mobi/china/6559/N7610.jar","file":"N7610.276.jar","type":"JAR"},{"url":"http://rugame.mobi/china/6559/1/N7610.jad","file":"N7610.279.jad","type":"JAD"}],"size":278},{"text":"176x220 : SE K700,K750 Chn<br/>\r\n<br/>176x220 : SE K550,K610,W350<br/>\r\n,W810,Z710 Chn  \r\n","links":[{"url":"http://rugame.mobi/china/6565/K700.jar","file":"K700.112.jar","type":"JAR"},{"url":"http://rugame.mobi/china/6565/1/K700.jad","file":"K700.115.jad","type":"JAD"}],"size":282},{"text":"208x208 : S60 3ed Chn  \r\n","links":[{"url":"http://rugame.mobi/china/6567/N5500.jar","file":"N5500.37.jar","type":"JAR"},{"url":"http://rugame.mobi/china/6567/1/N5500.jad","file":"N5500.37.jad","type":"JAD"}],"size":468},{"text":"240x320 : MOT E2,Z6,V8,U9,ZN5 Chn  \r\n","links":[{"url":"http://rugame.mobi/china/6561/E2.jar","file":"E2.219.jar","type":"JAR"},{"url":"http://rugame.mobi/china/6561/1/E2.jad","file":"E2.221.jad","type":"JAD"}],"size":499},{"text":"240x320 : S40 3ed Chn  \r\n","links":[{"url":"http://rugame.mobi/china/6564/N7370.jar","file":"N7370.282.jar","type":"JAR"},{"url":"http://rugame.mobi/china/6564/1/N7370.jad","file":"N7370.285.jad","type":"JAD"}],"size":500},{"text":"240x320 : S60 3ed Chn  \r\n","links":[{"url":"http://rugame.mobi/china/6563/n73.jar","file":"n73.1092.jar","type":"JAR"},{"url":"http://rugame.mobi/china/6563/1/n73.jad","file":"n73.1092.jad","type":"JAD"}],"size":504},{"text":"240x320 : SE K770,K800,S500<br/>\r\n,T650,W850 Chn  \r\n","links":[{"url":"http://rugame.mobi/china/6566/K790.jar","file":"K790.228.jar","type":"JAR"},{"url":"http://rugame.mobi/china/6566/1/K790.jad","file":"K790.229.jad","type":"JAD"}],"size":500},{"text":"320x240 : S60 3ed Chn  \r\n","links":[{"url":"http://rugame.mobi/china/6560/E62.jar","file":"E62.253.jar","type":"JAR"},{"url":"http://rugame.mobi/china/6560/1/E62.jad","file":"E62.255.jad","type":"JAD"}],"size":466},{"text":"360x640 : S60 5ed Chn<br/>\r\n<br/>360x640 : SE U1i(Satio),U5I(VIVAZ),U8i Chn<br/>\r\n<br/>360x640 : SAM i8910,i8910U,M8000 Chn  \r\n<br>","links":[{"url":"http://rugame.mobi/china/6562/N97.jar","file":"N97.35.jar","type":"JAR"},{"url":"http://rugame.mobi/china/6562/1/N97.jad","file":"N97.36.jad","type":"JAD"}],"size":620}]}