{"id":"43327","name":"Vietnam Heroes","desc":"0KLQuNGAINC90LAg0YLQtdC80YMg0LLQvtC50L3RiyDQsiDQktGM0LXRgtC90LDQvNC1LiA8YnIvPjxici8+","add":"28 Окт 2010 09:20","dwn":"5754","vie":"3623","vnd":"Jarbull","upl":"Брем","cat":"Стрелялки","cmm":"14","s3D":false,"bt":false,"rating":{"rtg":"7/15","ups":"7","dws":"15","scr":-8},"files":[{"text":"240x320 : S40 3ed Eng<br/>\r\n240x320 : S60 3ed Eng<br/>\r\n240x320 : SE K770,K800,S500,T650,W850 Eng<br/>\r\n","links":[{"url":"http://rugame.mobi/game/43339/2/J_2b9WhpGxn3Q0UwOENyABEfLvv9ArlG6mcJmqE6NI8=/vietnam_heroes_240x320.jar","file":"vietnam_heroes_240x320.jar","type":"JAR"},{"url":"http://rugame.mobi/game/43339/1/J_2b9WhpGxn3Q0UwOENyABEfLvv9ArlG6mcJmqE6NI8=/vietnam_heroes_240x320.jad","file":"vietnam_heroes_240x320.jad","type":"JAD"}],"size":"633"}]}