{"name":"Greatest Boxing","desc":"0JHQvtC60YEgYyDQv9GP0YLRjNGOINCx0L7QudGG0LDQvNC4INC4INC/0L7Rh9GC0Lgg0YfRgtC+IDNEINCz0YDQsNGE0LjQutC+0LkgIDxpbWcgc3JjPSIvc21pbGUvcXVpY2svYmlnZ3Jpbi5naWYiIGFsdD0iYmlnZ3JpbiIgLz4gPGJyLz48YnIvPg==","add":"16 Июнь 2011 18:57","dwn":7656,"vie":10913,"vnd":"Jarbull","upl":"Stox","cat":"Драки","cmm":16,"rating":{"rtg":"21/10"},"files":[{"text":"128x160 : S40 2ed Eng<br/>\r\n128x160 : SE K310,K320,K500,W200,W300,Z530 Eng<br/>\r\n","links":[{"file":"gb_160_se.jar"},{"file":"gb_160_se.jad"}],"size":153},{"text":"176x208 : S60 2ed Eng<br/>\r\n176x220 : SE K550,K610,W350,W810,Z710 Eng<br/>\r\n","links":[{"file":"gb_176.jar"},{"file":"gb_176.jad"}],"size":177},{"text":"240x320 : S40 3ed Eng<br/>\r\n240x320 : S60 3ed Eng<br/>\r\n","links":[{"file":"gb_240_nok.jar"},{"file":"gb_240_nok.jad"}],"size":261},{"text":"240x320 : SE K770,K790,K800,S500,T650,W850 Eng<br/>\r\n","links":[{"file":"gb_240_se.jar"},{"file":"gb_240_se.jad"}],"size":261}]}