{"name":"Adventure Monkey","desc":"0J7Qv9C40YHQsNC90LjRjyDQvdC10YIu","add":"26 Июнь 2010 19:30","dwn":702,"vnd":"shenfasoft ","upl":"Stox","cat":"Логические","cmm":0,"rating":{"rtg":"2/0"},"files":[{"text":"176x208 : S60 2ed  \r\n","links":[{"file":"MHXYJN7610.jar"},{"file":"MHXYJN7610.jad"}],"size":278},{"text":"240x320 : S40 3ed  \r\n","links":[{"file":"MHXYJN7370.jar"},{"file":"MHXYJN7370.jad"}],"size":348},{"text":"240x320 : S60 3ed  \r\n","links":[{"file":"MHXYJN73.jar"},{"file":"MHXYJN73.jad"}],"size":348}]}