{"name":"Hundreds and Millions of Tycoon - Hard Road","desc":"0J7Qv9C40YHQsNC90LjRjyDQvdC10YIu","add":"21 Июль 2010 07:25","dwn":911,"upl":"Javlonjon","cat":"Стратегии","cmm":0,"rating":{"rtg":"1/1"},"files":[{"text":"128x160 : S40 2ed  \r\n","links":[{"file":"Hund_128x160s40.jar"},{"file":"Hund_128x160s40.jad"}],"size":101},{"text":"176x208 : S60 2ed  \r\n","links":[{"file":"Hund_176x208s60.jar"},{"file":"Hund_176x208s60.jad"}],"size":203},{"text":"240x320 : S40 3ed  \r\n","links":[{"file":"Hund_240x320s40.jar"},{"file":"Hund_240x320s40.jad"}],"size":217},{"text":"240x320 : SE K770,K800,S500,T650,W850  \r\n","links":[{"file":"Hund_240x320se.jar"},{"file":"Hund_240x320se.jad"}],"size":216},{"text":"240x320 : S60 3ed  \r\n","links":[{"file":"Hund_240x320s60.jar"},{"file":"Hund_240x320s60.jad"}],"size":216}]}